MANIFEST.in
README.md
requirements.txt
setup.py
product_images/__init__.py
product_images/actions.py
product_images/admin.py
product_images/fields.py
product_images/forms.py
product_images/models.py
product_images/urls.py
product_images/utils.py
product_images/views.py
product_images/widgets.py
product_images.egg-info/PKG-INFO
product_images.egg-info/SOURCES.txt
product_images.egg-info/dependency_links.txt
product_images.egg-info/requires.txt
product_images.egg-info/top_level.txt
product_images/locale/ru/LC_MESSAGES/django.mo
product_images/locale/ru/LC_MESSAGES/django.po
product_images/locale/uk/LC_MESSAGES/django.mo
product_images/locale/uk/LC_MESSAGES/django.po
product_images/migrations/0001_initial.py
product_images/migrations/0002_productimage_created.py
product_images/migrations/__init__.py
product_images/static/dropzone/dropzone.min.css
product_images/static/dropzone/dropzone.min.js
product_images/static/file-manager/file-manager.css
product_images/static/file-manager/file-manager.js
product_images/templates/product-admin-preview.html
product_images/templates/product-images-form.html