Metadata-Version: 2.1
Name: product-images
Version: 1.0.8
Summary: Django run app
Home-page: https://github.com/pmaigutyak/product-images
Author: Paul Maigutyak
Author-email: pmaigutyak@gmail.com
License: MIT
Download-URL: https://github.com/pmaigutyak/product-images/archive/1.0.8.tar.gz
Platform: UNKNOWN
